Workbook

Sheet Instrucciones
A1: Panel Early Crop - Archivo de carga de datos
A3: Este archivo alimenta el panel de campos. Esta estructurado en hojas:
A5: • Campos - Catalogo maestro. Se edita cuando se agrega o modifica un campo.
A6: • Arandano YYYY - Datos productivos y economicos del arandano por temporada.
A7: • Limon YYYY - Idem limon.
A8: • Cana YYYY - Idem cana de azucar.
A10: Como agregar una nueva temporada:
A11: 1. Duplicar la hoja de la temporada anterior del cultivo.
A12: 2. Cambiar el nombre a "CULTIVO YYYY" (ej. "Arandano 2027").
A13: 3. Actualizar la columna "temporada" a YYYY.
A14: 4. Cargar los valores reales de la nueva temporada.
A16: Como agregar un campo nuevo:
... A47: • Proyeccion_com — Parámetros FOB: % fresco, kg terceros, precios por año.

Sheet Campos
A1: id_campo | B1: cultivo | C1: nombre | D1: entidad | E1: agronomo | F1: hectareas
A2: AR01 | B2: arandano | C2: PDJ Sgto. Moya | D2: PDJ | E2: Carlino | F2: 77.5
A3: AR02 | B3: arandano | C3: La Loma | D3: Fruit Crop | E3: Carlino | F3: 42
A4: AR03 | B4: arandano | C4: La Angostura | D4: Fruit Crop | E4: Carlino | F4: 21.8
A5: AR04 | B5: arandano | C5: El Molino | D5: Fruit Crop | E5: Carlino | F5: 20
A6: AR05 | B6: arandano | C6: Palma Sola | D6: Fruit Crop | E6: Modernel | F6: 19.8
A7: AR06 | B7: arandano | C7: Orlando | D7: PDJ | E7: Carlino | F7: 0
A8: LM01 | B8: limon | C8: Yaquilo | D8: Fruit Crop | E8: Casadei | F8: 140
A9: LM02 | B9: limon | C9: Casanova | D9: Fruit Crop | E9: Casadei | F9: 40
A10: LM03 | B10: limon | C10: Tajamar | D10: Greenpack | E10: Casadei | F10: 130
A11: LM04 | B11: limon | C11: Monte Grande | D11: Greenpack | E11: Casadei | F11: 45
A12: CA01 | B12: cana | C12: Cana de Azucar | D12: Greenpack | E12: Casadei | F12: 100

Sheet Arandano_2026
A1: id_campo | B1: temporada | C1: kg_totales | D1: kg_ha | E1: costo_ha_usd | F1: ingreso_ha_usd | G1: precio_kg_usd | H1: plantas_ha | I1: edad_plantacion | J1: variedad_1_nombre | K1: variedad_1_pct | L1: variedad_2_nombre | M1: variedad_2_pct | N1: variedad_3_nombre | O1: variedad_3_pct | P1: variedad_4_nombre | Q1: variedad_4_pct | R1: variedad_5_nombre | S1: variedad_5_pct | T1: variedad_6_nombre | U1: variedad_6_pct
A2: AR01 | B2: 2026 | C2: 702372 | D2: =+C2/Campos!F2 -> 9062.8645 | E2: 12000 | F2: =+D2*G2 -> 40964.148 | G2: 4.52 | H2: 3432 | I2: 6 | J2: Emerald | K2: 0.45 | L2: Slender | M2: 0.35 | N2: Biloxi | O2: 0.2
A3: AR02 | B3: 2026 | C3: 382194 | D3: =+C3/Campos!F3 -> 9099.8571 | E3: 11500 | F3: =+D3*G3 -> 37400.413 | G3: 4.11 | H3: 3286 | I3: 4 | J3: Emerald | K3: 0.4 | L3: Tafi | M3: 0.35 | N3: Snowchaser | O3: 0.25
A4: AR03 | B4: 2026 | C4: 201890 | D4: =+C4/Campos!F4 -> 9261.0092 | E4: 13000 | F4: =+D4*G4 -> 46397.656 | G4: 5.01 | H4: 4495 | I4: 9 | J4: Emerald | K4: 0.6 | L4: Biloxi | M4: 0.4
A5: AR04 | B5: 2026 | C5: 64800 | D5: =+C5/Campos!F5 -> 3240 | E5: 12500 | F5: =+D5*G5 -> 14580 | G5: 4.5 | H5: 500 | I5: 1 | J5: Tafi | K5: 0.4 | L5: Snowchaser | M5: 0.35 | N5: Slender | O5: 0.25
A6: AR05 | B6: 2026 | C6: 244489 | D6: =+C6/Campos!F6 -> 12347.929 | E6: 11000 | F6: =+D6*G6 -> 40748.167 | G6: 3.3 | H6: 3283 | I6: 3 | J6: Emerald | K6: 0.3 | L6: Slender | M6: 0.3 | N6: Snowchaser | O6: 0.25 | P6: Naike | Q6: 0.15

Sheet Limon_2026
A1: id_campo | B1: temporada | C1: kg_totales | D1: kg_ha | E1: costo_ha_usd | F1: ingreso_ha_usd | G1: precio_kg_usd | H1: plantas_ha | I1: edad_plantacion | J1: variedad_1_nombre | K1: variedad_1_pct | L1: variedad_2_nombre | M1: variedad_2_pct | N1: variedad_3_nombre | O1: variedad_3_pct | P1: variedad_4_nombre | Q1: variedad_4_pct | R1: variedad_5_nombre | S1: variedad_5_pct | T1: variedad_6_nombre | U1: variedad_6_pct
A2: LM01 | B2: 2026 | C2: 4515420 | D2: =+C2/Campos!F8 -> 32253 | E2: 4200 | F2: =+D2*G2 -> 18835.752 | G2: 0.584 | H2: 474 | I2: 14 | J2: Eureka | K2: 0.7 | L2: Genova | M2: 0.3
A3: LM02 | B3: 2026 | C3: 1108688 | D3: =+C3/Campos!F9 -> 27717.2 | E3: 6000 | F3: =+D3*G3 -> 16186.845 | G3: 0.584 | H3: 413 | I3: 22 | J3: Eureka | K3: 0.6 | L3: Lisbon | M3: 0.4
A4: LM03 | B4: 2026 | C4: 2761449 | D4: =+C4/Campos!F10 -> 21241.915 | E4: 5000 | F4: =+D4*G4 -> 12405.279 | G4: 0.584 | H4: 373 | I4: 11 | J4: Eureka | K4: 0.5 | L4: Genova | M4: 0.3 | N4: Lisbon | O4: 0.2
A5: LM04 | B5: 2026 | C5: 213840 | D5: =+C5/Campos!F11 -> 4752 | E5: 4550 | F5: =+D5*G5 -> 2775.168 | G5: 0.584 | H5: 309 | I5: 8 | J5: Eureka | K5: 0.65 | L5: Genova | M5: 0.35

Sheet Cana_2026
A1: id_campo | B1: temporada | C1: kg_totales | D1: kg_ha | E1: costo_ha_usd | F1: ingreso_ha_usd | G1: precio_kg_usd | H1: plantas_ha | I1: edad_plantacion | J1: variedad_1_nombre | K1: variedad_1_pct | L1: variedad_2_nombre | M1: variedad_2_pct | N1: variedad_3_nombre | O1: variedad_3_pct | P1: variedad_4_nombre | Q1: variedad_4_pct | R1: variedad_5_nombre | S1: variedad_5_pct | T1: variedad_6_nombre | U1: variedad_6_pct
A2: CA01 | B2: 2026 | C2: 0 | D2: =IF(C2="","",C2/VLOOKUP(A2,Campos!$A:$F,6,FALSE())) -> 0 | E2: 0 | F2: =IF(OR(D2="",G2=""),"",D2*G2) -> 0 | G2: 0 | I2: 3

Sheet Plantaciones
A1: id_campo | B1: año | C1: tipo | D1: hectareas | E1: variedad | F1: pct_variedad
A2: AR04 | B2: 2026 | C2: nueva | D2: 16 | E2: por definir | F2: 1
A3: AR02 | B3: 2028 | C3: nueva | D3: 6 | E3: por definir | F3: 1
A4: AR02 | B4: 2028 | C4: recambio | D4: 4 | E4: por definir | F4: 1
A5: AR02 | B5: 2029 | C5: recambio | D5: 38 | E5: por definir | F5: 1
A6: AR01 | B6: 2027 | C6: nueva | D6: 9 | E6: por definir | F6: 1
A7: AR01 | B7: 2028 | C7: nueva | D7: 8.5 | E7: por definir | F7: 1
A8: AR01 | B8: 2028 | C8: recambio | D8: 21.5 | E8: por definir | F8: 1
A9: AR01 | B9: 2029 | C9: recambio | D9: 27 | E9: por definir | F9: 1
A10: AR01 | B10: 2030 | C10: recambio | D10: 29 | E10: por definir | F10: 1
A11: AR03 | B11: 2030 | C11: nueva | D11: 0.2 | E11: por definir | F11: 1
A12: AR03 | B12: 2030 | C12: recambio | D12: 21.8 | E12: por definir | F12: 1
A13: AR06 | B13: 2027 | C13: nueva | D13: 40 | E13: por definir | F13: 1
A14: AR06 | B14: 2028 | C14: nueva | D14: 30 | E14: por definir | F14: 1

Sheet Curvas_rinde
A1: variedad | B1: año_0 | C1: año_1 | D1: año_2 | E1: año_3 | F1: año_4 | G1: año_5 | H1: año_6 | I1: año_7 | J1: año_8 | K1: año_9 | L1: año_10 | M1: año_11 | N1: año_12 | O1: año_13 | P1: año_14 | Q1: año_15
A2: por definir | B2: 0 | C2: 500 | D2: 3000 | E2: 9000 | F2: 17800 | G2: 17800 | H2: 17800 | I2: 17800 | J2: 17800 | K2: 17800 | L2: 15500 | M2: 13500 | N2: 11500 | O2: 10000 | P2: 10000 | Q2: 10000
A3: Tafi | B3: 0 | C3: 500 | D3: 3000 | E3: 9000 | F3: 17800 | G3: 17800 | H3: 17800 | I3: 17800 | J3: 17800 | K3: 17800 | L3: 15500 | M3: 13500 | N3: 11500 | O3: 10000 | P3: 10000 | Q3: 10000
A4: Slender | B4: 0 | C4: 500 | D4: 3000 | E4: 9000 | F4: 17800 | G4: 17800 | H4: 17800 | I4: 17800 | J4: 17800 | K4: 17800 | L4: 15500 | M4: 13500 | N4: 11500 | O4: 10000 | P4: 10000 | Q4: 10000
A5: Naike | B5: 0 | C5: 500 | D5: 3000 | E5: 9000 | F5: 17800 | G5: 17800 | H5: 17800 | I5: 17800 | J5: 17800 | K5: 17800 | L5: 15500 | M5: 13500 | N5: 11500 | O5: 10000 | P5: 10000 | Q5: 10000
A6: Moya | B6: 0 | C6: 500 | D6: 3000 | E6: 9000 | F6: 17800 | G6: 17800 | H6: 17800 | I6: 17800 | J6: 17800 | K6: 17800 | L6: 15500 | M6: 13500 | N6: 11500 | O6: 10000 | P6: 10000 | Q6: 10000
A7: Pampa | B7: 0 | C7: 500 | D7: 3000 | E7: 9000 | F7: 17800 | G7: 17800 | H7: 17800 | I7: 17800 | J7: 17800 | K7: 17800 | L7: 15500 | M7: 13500 | N7: 11500 | O7: 10000 | P7: 10000 | Q7: 10000

Sheet Ingresos
A1: año | B1: entidad | C1: cultivo | D1: canal | E1: tipo | F1: mercado | G1: kg_miles | H1: precio_kg_usd | I1: ingreso_usd
A2: 2025 | B2: Early Crop | C2: arandano | D2: exportacion | E2: industria | F2: Europa | G2: 95.9 | H2: 3.55 | I2: =+G2*H2*1000 -> 340445
A3: 2025 | B3: Early Crop | C3: arandano | D3: exportacion | E3: fresco | F3: Europa | G3: 1185.4 | H3: 6.7308086 | I3: =+G3*H3*1000 -> 7978700.5
A4: 2025 | B4: Early Crop | C4: arandano | D4: mercado interno | E4: fresco | F4: mercado interno | G4: 127.1475 | H4: 9.75 | I4: =+G4*H4*1000 -> 1239688.1
A5: 2025 | B5: Early Crop | C5: arandano | D5: mercado interno | E5: industria | F5: mercado interno | G5: 349.6 | H5: 2.7509591 | I5: =+G5*H5*1000 -> 961735.3
A6: 2025 | B6: Early Crop | C6: limon | D6: exportacion | E6: fresco | F6: USA | G6: 1347.84 | H6: 1.0080119 | I6: =+G6*H6*1000 -> 1358638.8
A7: 2025 | B7: Early Crop | C7: limon | D7: exportacion | E7: fresco | F7: Europa UE | G7: 2171.772 | H7: 1.0707856 | I7: =+G7*H7*1000 -> 2325502.3
A8: 2025 | B8: Early Crop | C8: limon | D8: exportacion | E8: fresco | F8: Europa No-UE | G8: 2940.828 | H8: 0.85771139 | I8: =+G8*H8*1000 -> 2522381.7
A9: 2025 | B9: Early Crop | C9: limon | D9: mercado interno | E9: industria | F9: mercado interno | G9: 5767.8 | H9: 0.1356 | I9: =+G9*H9*1000 -> 782113.68
A10: 2025 | B10: Early Crop | C10: cana | D10: — | E10: — | F10: — | I10: =IF(OR(G10="",H10=""),"",G10*1000*H10)
A11: 2025 | B11: Greenpack | C11: empaque | D11: — | E11: — | F11: — | I11: 1161700
A12: 2026 | B12: Early Crop | C12: arandano | D12: exportacion | E12: industria | F12: Europa | G12: 135 | H12: 2.8 | I12: =+G12*H12*1000 -> 378000
A13: 2026 | B13: Early Crop | C13: arandano | D13: exportacion | E13: fresco | F13: Europa | G13: 1091.6 | H13: 7.4588677 | I13: =+G13*H13*1000 -> 8142100
A14: 2026 | B14: Early Crop | C14: arandano | D14: mercado interno | E14: fresco | F14: mercado interno | G14: 171.4 | H14: 8.0268378 | I14: =+G14*H14*1000 -> 1375800
A15: 2026 | B15: Early Crop | C15: arandano | D15: mercado interno | E15: industria | F15: mercado interno | G15: 402 | H15: 2.8 | I15: =+G15*H15*1000 -> 1125600
A16: 2026 | B16: Early Crop | C16: limon | D16: exportacion | E16: fresco | F16: USA | G16: 3913.92 | H16: 0.97 | I16: =+G16*H16*1000 -> 3796502.4
A17: 2026 | B17: Early Crop | C17: limon | D17: exportacion | E17: fresco | F17: Europa UE | G17: 4872.96 | H17: 0.97 | I17: =+G17*H17*1000 -> 4726771.2
A18: 2026 | B18: Early Crop | C18: limon | D18: exportacion | E18: fresco | F18: Europa No-UE | G18: 4790.208 | H18: 0.97 | I18: =+G18*H18*1000 -> 4646501.8
A19: 2026 | B19: Early Crop | C19: limon | D19: mercado interno | E19: industria | F19: mercado interno | G19: 11540 | H19: 0.156 | I19: =+G19*H19*1000 -> 1800240
A20: 2026 | B20: Early Crop | C20: cana | D20: — | E20: — | F20: — | I20: =IF(OR(G20="",H20=""),"",G20*1000*H20)
A21: 2026 | B21: Greenpack | C21: empaque | D21: — | E21: — | F21: — | I21: 1973600

Sheet Proyeccion_com
A1: Panel Early Crop — Proyección de Ingresos Comerciales
A2: Ingreso = (kg propios × % canal + kg terceros) × precio FOB | USD
A3: 🟡 Amarillo = editable ⬜ Gris = calculado (no editar)
A5: PRECIOS FOB DE REFERENCIA — calculados desde hoja Ingresos (2026)
A6: Cultivo | B6: Canal | C6: kg totales | D6: Precio FOB (USD/kg)
A7: Arándano | B7: Fresco | C7: 1263000 | D7: 7.5359
A8: Arándano | B8: Industria | C8: 537000 | D8: 2.8
A9: Limón | B9: Fresco | C9: 13577088 | D9: 0.97
A10: Limón | B10: Industria | C10: 11540000 | D10: 0.156
A13: PARÁMETROS EDITABLES Y PROYECCIÓN DE INGRESOS
A14: Cultivo | B14: Variable | C14: 2026 | D14: 2027 | E14: 2028 | F14: 2029 | G14: 2030 | H14: 2031 | I14: 2032 | J14: 2033 | K14: 2034 | L14: 2035 | M14: 2036
A15: Arándano | B15: % fresco vs industria | C15: 0.7017 | D15: 0.7017 | E15: 0.7017 | F15: 0.7017 | G15: 0.7017 | H15: 0.7017 | I15: 0.7017 | J15: 0.7017 | K15: 0.7017 | L15: 0.7017 | M15: 0.7017
B16: kg terceros fresco | C16: =+Kg_proyectados!B13*Proyeccion_com!C15 -> 0 | D16: =+Kg_proyectados!C13*Proyeccion_com!D15 -> 26313.75 | E16: =+Kg_proyectados!D13*Proyeccion_com!E15 -> 157882.5 | F16: =+Kg_proyectados!E13*Proyeccion_com!F15 -> 473647.5 | G16: =+Kg_proyectados!F13*Proyeccion_com!G15 -> 936769.5 | H16: =+Kg_proyectados!G13*Proyeccion_com!H15 -> 936769.5 | I16: =+Kg_proyectados!H13*Proyeccion_com!I15 -> 936769.5 | J16: =+Kg_proyectados!I13*Proyeccion_com!J15 -> 936769.5 | ... M16: =+Kg_proyectados!L13*Proyeccion_com!M15 -> 815726.25
B17: kg terceros industria | C17: =+Kg_proyectados!B13*(1-Proyeccion_com!C15) -> 0 | D17: =+Kg_proyectados!C13*(1-Proyeccion_com!D15) -> 11186.25 | E17: =+Kg_proyectados!D13*(1-Proyeccion_com!E15) -> 67117.5 | F17: =+Kg_proyectados!E13*(1-Proyeccion_com!F15) -> 201352.5 | G17: =+Kg_proyectados!F13*(1-Proyeccion_com!G15) -> 398230.5 | H17: =+Kg_proyectados!G13*(1-Proyeccion_com!H15) -> 398230.5 | I17: =+Kg_proyectados!H13*(1-Proyeccion_com!I15) -> 398230.5 | J17: =+Kg_proyectados!I13*(1-Proyeccion_com!J15) -> 398230.5 | ... M17: =+Kg_proyectados!L13*(1-Proyeccion_com!M15) -> 346773.75
B18: precio FOB fresco (USD/kg) | C18: =$D$7 -> 7.5359 | D18: =$D$7 -> 7.5359 | E18: =$D$7 -> 7.5359 | F18: =$D$7 -> 7.5359 | G18: =$D$7 -> 7.5359 | H18: =$D$7 -> 7.5359 | I18: =$D$7 -> 7.5359 | J18: =$D$7 -> 7.5359 | ... M18: =$D$7 -> 7.5359
B19: precio FOB industria (USD/kg) | C19: =$D$8 -> 2.8 | D19: =$D$8 -> 2.8 | E19: =$D$8 -> 2.8 | F19: =$D$8 -> 2.8 | G19: =$D$8 -> 2.8 | H19: =$D$8 -> 2.8 | I19: =$D$8 -> 2.8 | J19: =$D$8 -> 2.8 | ... M19: =$D$8 -> 2.8
B20: → INGRESO TOTAL (USD) | C20: =(Kg_proyectados!B12*C15+C16)*C18+(Kg_proyectados!B12*(1-C15)+C17)*C19 -> 9820021 | D20: =(Kg_proyectados!C12*D15+D16)*D18+(Kg_proyectados!C12*(1-D15)+D17)*D19 -> 10322122 | E20: =(Kg_proyectados!D12*E15+E16)*E18+(Kg_proyectados!D12*(1-E15)+E17)*E19 -> 11024751 | F20: =(Kg_proyectados!E12*F15+F16)*F18+(Kg_proyectados!E12*(1-F15)+F17)*F19 -> 12872776 | G20: =(Kg_proyectados!F12*G15+G16)*G18+(Kg_proyectados!F12*(1-G15)+G17)*G19 -> 19103033 | H20: =(Kg_proyectados!G12*H15+H16)*H18+(Kg_proyectados!G12*(1-H15)+H17)*H19 -> 27684671 | I20: =(Kg_proyectados!H12*I15+I16)*I18+(Kg_proyectados!H12*(1-I15)+I17)*I19 -> 34677344 | J20: =(Kg_proyectados!I12*J15+J16)*J18+(Kg_proyectados!I12*(1-J15)+J17)*J19 -> 37425427 | ... M20: =(Kg_proyectados!L12*M15+M16)*M18+(Kg_proyectados!L12*(1-M15)+M17)*M19 -> 35821154
A21: Limón | B21: % fresco vs industria | C21: 0.5406 | D21: 0.5406 | E21: 0.5406 | F21: 0.5406 | G21: 0.5406 | H21: 0.5406 | I21: 0.5406 | J21: 0.5406 | K21: 0.5406 | L21: 0.5406 | M21: 0.5406
B22: kg terceros fresco | C22: =+Kg_proyectados!B20*Proyeccion_com!C21 -> 8929416.2 | D22: =+Kg_proyectados!C20*Proyeccion_com!D21 -> 10907941 | E22: =+Kg_proyectados!D20*Proyeccion_com!E21 -> 15773341 | F22: =+Kg_proyectados!E20*Proyeccion_com!F21 -> 20227102 | G22: =+Kg_proyectados!F20*Proyeccion_com!G21 -> 21299966 | H22: =+Kg_proyectados!G20*Proyeccion_com!H21 -> 21299966 | I22: =+Kg_proyectados!H20*Proyeccion_com!I21 -> 21299966 | J22: =+Kg_proyectados!I20*Proyeccion_com!J21 -> 21299966 | ... M22: =+Kg_proyectados!L20*Proyeccion_com!M21 -> 21299966
B23: kg terceros industria | C23: =+Kg_proyectados!B20*(1-Proyeccion_com!C21) -> 7588186.8 | D23: =+Kg_proyectados!C20*(1-Proyeccion_com!D21) -> 9269530.6 | E23: =+Kg_proyectados!D20*(1-Proyeccion_com!E21) -> 13404131 | F23: =+Kg_proyectados!E20*(1-Proyeccion_com!F21) -> 17188921 | G23: =+Kg_proyectados!F20*(1-Proyeccion_com!G21) -> 18100637 | H23: =+Kg_proyectados!G20*(1-Proyeccion_com!H21) -> 18100637 | I23: =+Kg_proyectados!H20*(1-Proyeccion_com!I21) -> 18100637 | J23: =+Kg_proyectados!I20*(1-Proyeccion_com!J21) -> 18100637 | ... M23: =+Kg_proyectados!L20*(1-Proyeccion_com!M21) -> 18100637
B24: precio FOB fresco (USD/kg) | C24: =$D$9 -> 0.97 | D24: =$D$9 -> 0.97 | E24: =$D$9 -> 0.97 | F24: =$D$9 -> 0.97 | G24: =$D$9 -> 0.97 | H24: =$D$9 -> 0.97 | I24: =$D$9 -> 0.97 | J24: =$D$9 -> 0.97 | ... M24: =$D$9 -> 0.97
B25: precio FOB industria (USD/kg) | C25: =$D$10 -> 0.156 | D25: =$D$10 -> 0.156 | E25: =$D$10 -> 0.156 | F25: =$D$10 -> 0.156 | G25: =$D$10 -> 0.156 | H25: =$D$10 -> 0.156 | I25: =$D$10 -> 0.156 | J25: =$D$10 -> 0.156 | ... M25: =$D$10 -> 0.156
B26: → INGRESO TOTAL (USD) | C26: =(Kg_proyectados!B19*C21+C22)*C24+(Kg_proyectados!B19*(1-C21)+C23)*C25 -> 14970948 | D26: =(Kg_proyectados!C19*D21+D22)*D24+(Kg_proyectados!C19*(1-D21)+D23)*D25 -> 17881452 | E26: =(Kg_proyectados!D19*E21+E22)*E24+(Kg_proyectados!D19*(1-E21)+E23)*E25 -> 23841936 | F26: =(Kg_proyectados!E19*F21+F22)*F24+(Kg_proyectados!E19*(1-F21)+F23)*F25 -> 28610323 | G26: =(Kg_proyectados!F19*G21+G22)*G24+(Kg_proyectados!F19*(1-G21)+G23)*G25 -> 28610323 | H26: =(Kg_proyectados!G19*H21+H22)*H24+(Kg_proyectados!G19*(1-H21)+H23)*H25 -> 28610323 | I26: =(Kg_proyectados!H19*I21+I22)*I24+(Kg_proyectados!H19*(1-I21)+I23)*I25 -> 28610323 | J26: =(Kg_proyectados!I19*J21+J22)*J24+(Kg_proyectados!I19*(1-J21)+J23)*J25 -> 28610323 | ... M26: =(Kg_proyectados!L19*M21+M22)*M24+(Kg_proyectados!L19*(1-M21)+M23)*M25 -> 28610323
A27: Caña | B27: % fresco vs industria | C27: 0 | D27: 0 | E27: 0 | F27: 0 | G27: 0 | H27: 0 | I27: 0 | J27: 0 | K27: 0 | L27: 0 | M27: 0
B28: kg terceros fresco | C28: 0 | D28: 0 | E28: 0 | F28: 0 | G28: 0 | H28: 0 | I28: 0 | J28: 0 | K28: 0 | L28: 0 | M28: 0
B29: kg terceros industria | C29: 0 | D29: 0 | E29: 0 | F29: 0 | G29: 0 | H29: 0 | I29: 0 | J29: 0 | K29: 0 | L29: 0 | M29: 0
B30: precio FOB fresco (USD/kg) | C30: 0 | D30: 0 | E30: 0 | F30: 0 | G30: 0 | H30: 0 | I30: 0 | J30: 0 | K30: 0 | L30: 0 | M30: 0
B31: precio FOB industria (USD/kg) | C31: 0 | D31: 0 | E31: 0 | F31: 0 | G31: 0 | H31: 0 | I31: 0 | J31: 0 | K31: 0 | L31: 0 | M31: 0
B32: → INGRESO TOTAL (USD) | C32: 0 | D32: 0 | E32: 0 | F32: 0 | G32: 0 | H32: 0 | I32: 0 | J32: 0 | K32: 0 | L32: 0 | M32: 0
A33: TOTAL | B33: → INGRESO TOTAL (USD) | C33: =C20+C26+C32 -> 24790969 | D33: =D20+D26+D32 -> 28203574 | E33: =E20+E26+E32 -> 34866687 | F33: =F20+F26+F32 -> 41483099 | G33: =G20+G26+G32 -> 47713356 | H33: =H20+H26+H32 -> 56294994 | I33: =I20+I26+I32 -> 63287667 | J33: =J20+J26+J32 -> 66035751 | ... M33: =M20+M26+M32 -> 64431477
A35: Kg propios → hoja Kg_proyectados | Precios FOB → tabla de referencia superior | Solo editá celdas amarillas: % fresco/industria y kg terceros.

Sheet Kg_proyectados
A1: Kg proyectados por campo y año — fórmulas desde Campos, Arandano_2026, Plantaciones y Curvas_rinde
A2: Recambios: se descuentan de plantas existentes y se suman como nuevas plantaciones (misma lógica que el dashboard).
A4: Campo | B4: 2026 | C4: 2027 | D4: 2028 | E4: 2029 | F4: 2030 | G4: 2031 | H4: 2032 | I4: 2033 | J4: 2034 | K4: 2035 | L4: 2036
A5: — ARÁNDANO —
A6: PDJ Sgto. Moya | B6: =MAX(0,Campos!$F$2)*Arandano_2026!$D$2 -> 702372 | C6: =MAX(0,Campos!$F$2)*Arandano_2026!$D$2+9*Curvas_rinde!C$2 -> 706872 | D6: =MAX(0,Campos!$F$2-(21.5))*Arandano_2026!$D$2+9*Curvas_rinde!D$2+8.5*Curvas_rinde!C$2+21.5*Curvas_rinde!C$2 -> 549520.41 | E6: =MAX(0,Campos!$F$2-(21.5+27))*Arandano_2026!$D$2+9*Curvas_rinde!E$2+8.5*Curvas_rinde!D$2+21.5*Curvas_rinde!D$2+27*Curvas_rinde!C$2 -> 447323.07 | F6: =MAX(0,Campos!$F$2-(21.5+27+29))*Arandano_2026!$D$2+9*Curvas_rinde!F$2+8.5*Curvas_rinde!E$2+21.5*Curvas_rinde!E$2+27*Curvas_rinde!D$2+29*Curvas_rinde!C$2 -> 525700 | G6: =MAX(0,Campos!$F$2-(21.5+27+29))*Arandano_2026!$D$2+9*Curvas_rinde!G$2+8.5*Curvas_rinde!F$2+21.5*Curvas_rinde!F$2+27*Curvas_rinde!E$2+29*Curvas_rinde!D$2 -> 1024200 | H6: =MAX(0,Campos!$F$2-(21.5+27+29))*Arandano_2026!$D$2+9*Curvas_rinde!H$2+8.5*Curvas_rinde!G$2+21.5*Curvas_rinde!G$2+27*Curvas_rinde!F$2+29*Curvas_rinde!E$2 -> 1435800 | I6: =MAX(0,Campos!$F$2-(21.5+27+29))*Arandano_2026!$D$2+9*Curvas_rinde!I$2+8.5*Curvas_rinde!H$2+21.5*Curvas_rinde!H$2+27*Curvas_rinde!G$2+29*Curvas_rinde!F$2 -> 1691000 | J6: =MAX(0,Campos!$F$2-(21.5+27+29))*Arandano_2026!$D$2+9*Curvas_rinde!J$2+8.5*Curvas_rinde!I$2+21.5*Curvas_rinde!I$2+27*Curvas_rinde!H$2+29*Curvas_rinde!G$2 -> 1691000 | K6: =MAX(0,Campos!$F$2-(21.5+27+29))*Arandano_2026!$D$2+9*Curvas_rinde!K$2+8.5*Curvas_rinde!J$2+21.5*Curvas_rinde!J$2+27*Curvas_rinde!I$2+29*Curvas_rinde!H$2 -> 1691000 | L6: =MAX(0,Campos!$F$2-(21.5+27+29))*Arandano_2026!$D$2+9*Curvas_rinde!L$2+8.5*Curvas_rinde!K$2+21.5*Curvas_rinde!K$2+27*Curvas_rinde!J$2+29*Curvas_rinde!I$2 -> 1670300
A7: La Loma | B7: =MAX(0,Campos!$F$3)*Arandano_2026!$D$3 -> 382194 | C7: =MAX(0,Campos!$F$3)*Arandano_2026!$D$3 -> 382194 | D7: =MAX(0,Campos!$F$3-(4))*Arandano_2026!$D$3+6*Curvas_rinde!C$2+4*Curvas_rinde!C$2 -> 350794.57 | E7: =MAX(0,Campos!$F$3-(4+38))*Arandano_2026!$D$3+6*Curvas_rinde!D$2+4*Curvas_rinde!D$2+38*Curvas_rinde!C$2 -> 49000 | F7: =MAX(0,Campos!$F$3-(4+38))*Arandano_2026!$D$3+6*Curvas_rinde!E$2+4*Curvas_rinde!E$2+38*Curvas_rinde!D$2 -> 204000 | G7: =MAX(0,Campos!$F$3-(4+38))*Arandano_2026!$D$3+6*Curvas_rinde!F$2+4*Curvas_rinde!F$2+38*Curvas_rinde!E$2 -> 520000 | H7: =MAX(0,Campos!$F$3-(4+38))*Arandano_2026!$D$3+6*Curvas_rinde!G$2+4*Curvas_rinde!G$2+38*Curvas_rinde!F$2 -> 854400 | I7: =MAX(0,Campos!$F$3-(4+38))*Arandano_2026!$D$3+6*Curvas_rinde!H$2+4*Curvas_rinde!H$2+38*Curvas_rinde!G$2 -> 854400 | J7: =MAX(0,Campos!$F$3-(4+38))*Arandano_2026!$D$3+6*Curvas_rinde!I$2+4*Curvas_rinde!I$2+38*Curvas_rinde!H$2 -> 854400 | K7: =MAX(0,Campos!$F$3-(4+38))*Arandano_2026!$D$3+6*Curvas_rinde!J$2+4*Curvas_rinde!J$2+38*Curvas_rinde!I$2 -> 854400 | L7: =MAX(0,Campos!$F$3-(4+38))*Arandano_2026!$D$3+6*Curvas_rinde!K$2+4*Curvas_rinde!K$2+38*Curvas_rinde!J$2 -> 854400
A8: La Angostura | B8: =MAX(0,Campos!$F$4)*Arandano_2026!$D$4 -> 201890 | C8: =MAX(0,Campos!$F$4)*Arandano_2026!$D$4 -> 201890 | D8: =MAX(0,Campos!$F$4)*Arandano_2026!$D$4 -> 201890 | E8: =MAX(0,Campos!$F$4)*Arandano_2026!$D$4 -> 201890 | F8: =MAX(0,Campos!$F$4-(21.8))*Arandano_2026!$D$4+0.2*Curvas_rinde!C$2+21.8*Curvas_rinde!C$2 -> 11000 | G8: =MAX(0,Campos!$F$4-(21.8))*Arandano_2026!$D$4+0.2*Curvas_rinde!D$2+21.8*Curvas_rinde!D$2 -> 66000 | H8: =MAX(0,Campos!$F$4-(21.8))*Arandano_2026!$D$4+0.2*Curvas_rinde!E$2+21.8*Curvas_rinde!E$2 -> 198000 | I8: =MAX(0,Campos!$F$4-(21.8))*Arandano_2026!$D$4+0.2*Curvas_rinde!F$2+21.8*Curvas_rinde!F$2 -> 391600 | J8: =MAX(0,Campos!$F$4-(21.8))*Arandano_2026!$D$4+0.2*Curvas_rinde!G$2+21.8*Curvas_rinde!G$2 -> 391600 | K8: =MAX(0,Campos!$F$4-(21.8))*Arandano_2026!$D$4+0.2*Curvas_rinde!H$2+21.8*Curvas_rinde!H$2 -> 391600 | L8: =MAX(0,Campos!$F$4-(21.8))*Arandano_2026!$D$4+0.2*Curvas_rinde!I$2+21.8*Curvas_rinde!I$2 -> 391600
A9: El Molino | B9: =MAX(0,Campos!$F$5)*Arandano_2026!$D$5+16*Curvas_rinde!C$2 -> 72800 | C9: =MAX(0,Campos!$F$5)*Arandano_2026!$D$5+16*Curvas_rinde!D$2 -> 112800 | D9: =MAX(0,Campos!$F$5)*Arandano_2026!$D$5+16*Curvas_rinde!E$2 -> 208800 | E9: =MAX(0,Campos!$F$5)*Arandano_2026!$D$5+16*Curvas_rinde!F$2 -> 349600 | F9: =MAX(0,Campos!$F$5)*Arandano_2026!$D$5+16*Curvas_rinde!G$2 -> 349600 | G9: =MAX(0,Campos!$F$5)*Arandano_2026!$D$5+16*Curvas_rinde!H$2 -> 349600 | H9: =MAX(0,Campos!$F$5)*Arandano_2026!$D$5+16*Curvas_rinde!I$2 -> 349600 | I9: =MAX(0,Campos!$F$5)*Arandano_2026!$D$5+16*Curvas_rinde!J$2 -> 349600 | ... L9: =MAX(0,Campos!$F$5)*Arandano_2026!$D$5+16*Curvas_rinde!M$2 -> 280800
A10: Palma Sola | B10: =MAX(0,Campos!$F$6)*Arandano_2026!$D$6 -> 244489 | C10: =MAX(0,Campos!$F$6)*Arandano_2026!$D$6 -> 244489 | D10: =MAX(0,Campos!$F$6)*Arandano_2026!$D$6 -> 244489 | E10: =MAX(0,Campos!$F$6)*Arandano_2026!$D$6 -> 244489 | F10: =MAX(0,Campos!$F$6)*Arandano_2026!$D$6 -> 244489 | G10: =MAX(0,Campos!$F$6)*Arandano_2026!$D$6 -> 244489 | H10: =MAX(0,Campos!$F$6)*Arandano_2026!$D$6 -> 244489 | I10: =MAX(0,Campos!$F$6)*Arandano_2026!$D$6 -> 244489 | ... L10: =MAX(0,Campos!$F$6)*Arandano_2026!$D$6 -> 244489
A11: Orlando | B11: =MAX(0,Campos!$F$7)*0 -> 0 | C11: =MAX(0,Campos!$F$7)*0+40*Curvas_rinde!B$2 -> 0 | D11: =MAX(0,Campos!$F$7)*0+40*Curvas_rinde!C$2+30*Curvas_rinde!B$2 -> 20000 | E11: =MAX(0,Campos!$F$7)*0+40*Curvas_rinde!D$2+30*Curvas_rinde!C$2 -> 135000 | F11: =MAX(0,Campos!$F$7)*0+40*Curvas_rinde!E$2+30*Curvas_rinde!D$2 -> 450000 | G11: =MAX(0,Campos!$F$7)*0+40*Curvas_rinde!F$2+30*Curvas_rinde!E$2 -> 982000 | H11: =MAX(0,Campos!$F$7)*0+40*Curvas_rinde!G$2+30*Curvas_rinde!F$2 -> 1246000 | I11: =MAX(0,Campos!$F$7)*0+40*Curvas_rinde!H$2+30*Curvas_rinde!G$2 -> 1246000 | J11: =MAX(0,Campos!$F$7)*0+40*Curvas_rinde!I$2+30*Curvas_rinde!H$2 -> 1246000 | K11: =MAX(0,Campos!$F$7)*0+40*Curvas_rinde!J$2+30*Curvas_rinde!I$2 -> 1246000 | L11: =MAX(0,Campos!$F$7)*0+40*Curvas_rinde!K$2+30*Curvas_rinde!J$2 -> 1246000
A12: Total Arándano | B12: =SUM(B6,B7,B8,B9,B10,B11) -> 1603745 | C12: =SUM(C6,C7,C8,C9,C10,C11) -> 1648245 | D12: =SUM(D6,D7,D8,D9,D10,D11) -> 1575494 | E12: =SUM(E6,E7,E8,E9,E10,E11) -> 1427302.1 | F12: =SUM(F6,F7,F8,F9,F10,F11) -> 1784789 | G12: =SUM(G6,G7,G8,G9,G10,G11) -> 3186289 | H12: =SUM(H6,H7,H8,H9,H10,H11) -> 4328289 | I12: =SUM(I6,I7,I8,I9,I10,I11) -> 4777089 | ... L12: =SUM(L6,L7,L8,L9,L10,L11) -> 4687589
A13: fruta terceros | B13: =75*Curvas_rinde!B2 -> 0 | C13: =75*Curvas_rinde!C2 -> 37500 | D13: =75*Curvas_rinde!D2 -> 225000 | E13: =75*Curvas_rinde!E2 -> 675000 | F13: =75*Curvas_rinde!F2 -> 1335000 | G13: =75*Curvas_rinde!G2 -> 1335000 | H13: =75*Curvas_rinde!H2 -> 1335000 | I13: =75*Curvas_rinde!I2 -> 1335000 | ... L13: =75*Curvas_rinde!L2 -> 1162500
A14: — LIMÓN —
A15: Yaquilo | B15: =Campos!$F$8*Limon_2026!$D$2 -> 4515420 | C15: 5500000 | D15: 6000000 | E15: 6500000 | F15: =Campos!$F$8*Limon_2026!$D$2 -> 4515420 | G15: =Campos!$F$8*Limon_2026!$D$2 -> 4515420 | H15: =Campos!$F$8*Limon_2026!$D$2 -> 4515420 | I15: =Campos!$F$8*Limon_2026!$D$2 -> 4515420 | J15: =Campos!$F$8*Limon_2026!$D$2 -> 4515420 | K15: =Campos!$F$8*Limon_2026!$D$2 -> 4515420 | L15: =Campos!$F$8*Limon_2026!$D$2 -> 4515420
A16: Casanova | B16: =Campos!$F$9*Limon_2026!$D$3 -> 1108688 | C16: =Campos!$F$9*Limon_2026!$D$3 -> 1108688 | D16: =Campos!$F$9*Limon_2026!$D$3 -> 1108688 | E16: =Campos!$F$9*Limon_2026!$D$3 -> 1108688 | F16: =Campos!$F$9*Limon_2026!$D$3 -> 1108688 | G16: =Campos!$F$9*Limon_2026!$D$3 -> 1108688 | H16: =Campos!$F$9*Limon_2026!$D$3 -> 1108688 | I16: =Campos!$F$9*Limon_2026!$D$3 -> 1108688 | ... L16: =Campos!$F$9*Limon_2026!$D$3 -> 1108688
A17: Tajamar | B17: =Campos!$F$10*Limon_2026!$D$4 -> 2761449 | C17: 3000000 | D17: 3500000 | E17: =Campos!$F$10*Limon_2026!$D$4 -> 2761449 | F17: =Campos!$F$10*Limon_2026!$D$4 -> 2761449 | G17: =Campos!$F$10*Limon_2026!$D$4 -> 2761449 | H17: =Campos!$F$10*Limon_2026!$D$4 -> 2761449 | I17: =Campos!$F$10*Limon_2026!$D$4 -> 2761449 | J17: =Campos!$F$10*Limon_2026!$D$4 -> 2761449 | K17: =Campos!$F$10*Limon_2026!$D$4 -> 2761449 | L17: =Campos!$F$10*Limon_2026!$D$4 -> 2761449
A18: Monte Grande | B18: =Campos!$F$11*Limon_2026!$D$5 -> 213840 | C18: =Campos!$F$11*Limon_2026!$D$5 -> 213840 | D18: =Campos!$F$11*Limon_2026!$D$5 -> 213840 | E18: =Campos!$F$11*Limon_2026!$D$5 -> 213840 | F18: =Campos!$F$11*Limon_2026!$D$5 -> 213840 | G18: =Campos!$F$11*Limon_2026!$D$5 -> 213840 | H18: =Campos!$F$11*Limon_2026!$D$5 -> 213840 | I18: =Campos!$F$11*Limon_2026!$D$5 -> 213840 | ... L18: =Campos!$F$11*Limon_2026!$D$5 -> 213840
A19: Total Limón | B19: =SUM(B15,B16,B17,B18) -> 8599397 | C19: =SUM(C15,C16,C17,C18) -> 9822528 | D19: =SUM(D15,D16,D17,D18) -> 10822528 | E19: =SUM(E15,E16,E17,E18) -> 10583977 | F19: =SUM(F15,F16,F17,F18) -> 8599397 | G19: =SUM(G15,G16,G17,G18) -> 8599397 | H19: =SUM(H15,H16,H17,H18) -> 8599397 | I19: =SUM(I15,I16,I17,I18) -> 8599397 | ... L19: =SUM(L15,L16,L17,L18) -> 8599397
A20: fruta terceros | B20: =25117000-B19 -> 16517603 | C20: =30000000-C19 -> 20177472 | D20: =40000000-D19 -> 29177472 | E20: =48000000-E19 -> 37416023 | F20: =48000000-F19 -> 39400603 | G20: =48000000-G19 -> 39400603 | H20: =48000000-H19 -> 39400603 | I20: =48000000-I19 -> 39400603 | J20: =48000000-J19 -> 39400603 | K20: =48000000-K19 -> 39400603 | L20: =48000000-L19 -> 39400603
